README.md
setup.py
binance/__init__.py
binance/bind.py
binance/client.py
binance/models.py
binance/request.py
python_binance_api.egg-info/PKG-INFO
python_binance_api.egg-info/SOURCES.txt
python_binance_api.egg-info/dependency_links.txt
python_binance_api.egg-info/requires.txt
python_binance_api.egg-info/top_level.txt
python_binance_api.egg-info/zip-safe