Metadata-Version: 1.0
Name: python-binance-api
Version: 1.0.0
Summary: Binance API client
Home-page: http://github.com/cnfuyu/python-binance-api
Author: cnfuyu
Author-email: cnfuyu@gmail.com
License: MIT
Keywords: binance
Platform: UNKNOWN
